envlog/__init__.py
envlog/config.py
envlog/parser.py
envlog/py.typed
envlog-1.0.0.dist-info/licenses/LICENSE
envlog-1.0.0.dist-info/METADATA
envlog-1.0.0.dist-info/WHEEL
envlog-1.0.0.dist-info/top_level.txt
envlog-1.0.0.dist-info/RECORD
